float/__init__.py
float/change_detection/__init__.py
float/change_detection/base_change_detector.py
float/change_detection/erics.py
float/change_detection/evaluation/__init__.py
float/change_detection/evaluation/change_detection_evaluator.py
float/change_detection/evaluation/measures/__init__.py
float/change_detection/evaluation/measures/detected_change_rate.py
float/change_detection/evaluation/measures/detection_delay.py
float/change_detection/evaluation/measures/false_discovery_rate.py
float/change_detection/evaluation/measures/mean_time_ratio.py
float/change_detection/evaluation/measures/missed_detection_rate.py
float/change_detection/evaluation/measures/time_between_false_alarms.py
float/change_detection/river/__init__.py
float/change_detection/river/river_change_detector.py
float/change_detection/skmultiflow/__init__.py
float/change_detection/skmultiflow/skmultiflow_change_detector.py
float/change_detection/tornado/__init__.py
float/change_detection/tornado/adwin.py
float/change_detection/tornado/cusum.py
float/change_detection/tornado/ddm.py
float/change_detection/tornado/eddm.py
float/change_detection/tornado/ewma.py
float/change_detection/tornado/fhddm.py
float/change_detection/tornado/fhddms.py
float/change_detection/tornado/fhddms_add.py
float/change_detection/tornado/hddm_a.py
float/change_detection/tornado/hddm_w.py
float/change_detection/tornado/mddm_a.py
float/change_detection/tornado/mddm_e.py
float/change_detection/tornado/mddm_g.py
float/change_detection/tornado/page_hinkley.py
float/change_detection/tornado/rddm.py
float/change_detection/tornado/seqdrift2.py
float/data/__init__.py
float/data/data_loader.py
float/data/preprocessing/__init__.py
float/data/preprocessing/base_scaler.py
float/data/preprocessing/sklearn_scaler.py
float/feature_selection/__init__.py
float/feature_selection/base_feature_selector.py
float/feature_selection/efs.py
float/feature_selection/fires.py
float/feature_selection/fsds.py
float/feature_selection/ofs.py
float_evaluation-0.0.2.dist-info/LICENSE
float_evaluation-0.0.2.dist-info/METADATA
float_evaluation-0.0.2.dist-info/WHEEL
float_evaluation-0.0.2.dist-info/top_level.txt
float_evaluation-0.0.2.dist-info/RECORD
