Metadata-Version: 2.1
Name: float-evaluation
Version: 0.0.2
Summary: A modular Python framework for standardised evaluation and benchmarking of online learning models
Home-page: https://github.com/haugjo/float
Author: Johannes Haug
Author-email: johannes-christian.haug@uni-tuebingen.de
Project-URL: Documentation, https://haugjo.github.io/float/
Classifier: Programming Language :: Python :: 3
Classifier: License :: OSI Approved :: MIT License
Classifier: Operating System :: OS Independent
Requires-Python: >=3.8
License-File: LICENSE
Requires-Dist: numpy (>=1.22.1)
Requires-Dist: scikit-learn (>=1.0.2)
Requires-Dist: tabulate (>=0.8.5)
Requires-Dist: matplotlib (>=3.4.2)
Requires-Dist: scipy (>=1.7.3)
Requires-Dist: pandas (>=1.4.0)
Requires-Dist: river (>=0.9.0)
Requires-Dist: scikit-multiflow (>=0.5.3)
